Metadata-Version: 1.1
Name: jrun
Version: 0.1.1
Summary: Run jupyter notebooks as command line scripts with variable overrides
Home-page: https://github.com/lepisma/jrun
Author: Abhinav Tushar
Author-email: abhinav.tushar.vs@gmail.com
License: UNKNOWN
Platform: UNKNOWN
Classifier: License :: OSI Approved :: GNU General Public License v3 (GPLv3)
Classifier: Natural Language :: English
Classifier: Programming Language :: Python
Classifier: Programming Language :: Python :: 3 :: Only
